.DS_Store
cl-timer/__init__.py
cl-timer/__main__.py
cl-timer/art.py
cl-timer/graphics.py
cl-timer/scramble.py
cl-timer/test.py
cl-timer/timer.py
cl_timer/__init__.py
cl_timer/__main__.py
cl_timer/art.py
cl_timer/graphics.py
cl_timer/interpreter.py
cl_timer/scramble.py
cl_timer/test.py
cl_timer/timer.py
cl_timer/utils.py
cl_timer-1.1.4.dist-info/LICENSE
cl_timer-1.1.4.dist-info/METADATA
cl_timer-1.1.4.dist-info/WHEEL
cl_timer-1.1.4.dist-info/entry_points.txt
cl_timer-1.1.4.dist-info/top_level.txt
cl_timer-1.1.4.dist-info/RECORD
