Metadata-Version: 2.1
Name: cl-timer
Version: 1.1.4
Summary: A Cubing Timer for the Terminal
Home-page: https://github.com/lol-cubes/cl-timer
Author: Arin Khare
Author-email: arinmkhare@gmail.com
License: UNKNOWN
Platform: UNKNOWN
Classifier: Programming Language :: Python :: 3
Classifier: License :: OSI Approved :: MIT License
Requires-Python: >=3.7
